random_quote/__init__.py
random_quote/cli.py
tests/__init__.py
tests/test_cli.py
random_quote_cli-1.0.7.dist-info/METADATA
random_quote_cli-1.0.7.dist-info/WHEEL
random_quote_cli-1.0.7.dist-info/entry_points.txt
random_quote_cli-1.0.7.dist-info/top_level.txt
random_quote_cli-1.0.7.dist-info/RECORD
